{
  "run_name": "optimized_ragas_40q",
  "created_at": "2026-04-07T01:03:52",
  "base_url": "http://127.0.0.1:8000",
  "provider": "",
  "dataset_path": "C:\\Users\\24719\\Desktop\\RAG\\评测\\ragas评测集_40题.json",
  "题目总数": 40,
  "指标": {
    "忠诚度": 0.3986,
    "上下文召回率": 0.0,
    "答案准确度": 0.0,
    "平均token": 14395.48,
    "平均延迟_ms": 39080.38
  },
  "附加统计": {
    "平均输入token": 14027.38,
    "平均输出token": 368.1,
    "token可用题数": 40,
    "RAGAS可用题数": 0,
    "无检索上下文题数": 40,
    "延迟P50_ms": 35672.83,
    "延迟P95_ms": 62975.48,
    "失败题数": 0
  }
}